Orange3_Pumice-1.2.1-py3.11-nspkg.pth
orange3_pumice-1.2.1.dist-info/licenses/LICENSE.txt
orangecontrib/pumice/__init__.py
orangecontrib/pumice/datasets/cars.xlsx
orangecontrib/pumice/datasets/weather/C-MD-prcp.pkl.gz
orangecontrib/pumice/datasets/weather/C-MD-tavg.pkl.gz
orangecontrib/pumice/datasets/weather/C-MD-tmax.pkl.gz
orangecontrib/pumice/datasets/weather/C-MD-tmin.pkl.gz
orangecontrib/pumice/datasets/weather/C-MT-prcp.pkl.gz
orangecontrib/pumice/datasets/weather/C-MT-tavg.pkl.gz
orangecontrib/pumice/datasets/weather/C-MT-tmax.pkl.gz
orangecontrib/pumice/datasets/weather/C-MT-tmin.pkl.gz
orangecontrib/pumice/datasets/weather/README.md
orangecontrib/pumice/datasets/weather/S-M2024-prcp.pkl.gz
orangecontrib/pumice/datasets/weather/S-M2024-tavg.pkl.gz
orangecontrib/pumice/datasets/weather/S-M2024-tmax.pkl.gz
orangecontrib/pumice/datasets/weather/S-M2024-tmin.pkl.gz
orangecontrib/pumice/datasets/weather/S-MD-prcp.pkl.gz
orangecontrib/pumice/datasets/weather/S-MD-tavg.pkl.gz
orangecontrib/pumice/datasets/weather/S-MD-tmax.pkl.gz
orangecontrib/pumice/datasets/weather/S-MD-tmin.pkl.gz
orangecontrib/pumice/datasets/weather/S-MT-prcp.pkl.gz
orangecontrib/pumice/datasets/weather/S-MT-tavg.pkl.gz
orangecontrib/pumice/datasets/weather/S-MT-tmax.pkl.gz
orangecontrib/pumice/datasets/weather/S-MT-tmin.pkl.gz
orangecontrib/pumice/datasets/weather/countries.pkl.gz
orangecontrib/pumice/datasets/weather/station-data.pkl.gz
orangecontrib/pumice/i18n/English.json
orangecontrib/pumice/i18n/Slovenian.json
orangecontrib/pumice/widgets/__init__.py
orangecontrib/pumice/widgets/owclimatedata.py
orangecontrib/pumice/widgets/owcompair.py
orangecontrib/pumice/widgets/owrecommendation.py
orangecontrib/pumice/widgets/icons/category.svg
orangecontrib/pumice/widgets/icons/climatedata.svg
orangecontrib/pumice/widgets/icons/compair.svg
orangecontrib/pumice/widgets/icons/recommendation.svg
orangecontrib/pumice/widgets/tests/__init__.py
orangecontrib/pumice/widgets/tests/test_owrecommendation.py
orange3_pumice-1.2.1.dist-info/METADATA
orange3_pumice-1.2.1.dist-info/WHEEL
orange3_pumice-1.2.1.dist-info/entry_points.txt
orange3_pumice-1.2.1.dist-info/namespace_packages.txt
orange3_pumice-1.2.1.dist-info/top_level.txt
orange3_pumice-1.2.1.dist-info/RECORD
