Metadata-Version: 2.4
Name: Orange3-Pumice
Version: 1.2.1
Summary: Educational widgets for project Pumice
Home-page: https://github.com/biolab/orange3-pumice
Author: Bioinformatics Laboratory, FRI UL
Author-email: contact@orange.biolab.si
License: BSD
Keywords: orange3 add-on
License-File: LICENSE.txt
Requires-Dist: Orange3>=3.38.1
Requires-Dist: orange3-network>=1.10.1
Requires-Dist: orange3-imageanalytics
Requires-Dist: orange-canvas-core>=0.2.2
Requires-Dist: orange-widget-base>=4.23.0
Provides-Extra: doc
Requires-Dist: sphinx; extra == "doc"
Requires-Dist: recommonmark; extra == "doc"
Requires-Dist: sphinx_rtd_theme; extra == "doc"
Provides-Extra: test
Requires-Dist: coverage; extra == "test"
Dynamic: author
Dynamic: author-email
Dynamic: description
Dynamic: description-content-type
Dynamic: home-page
Dynamic: keywords
Dynamic: license
Dynamic: license-file
Dynamic: provides-extra
Dynamic: requires-dist
Dynamic: summary
